piwaterflow/__init__.py
piwaterflow/__main__.py
piwaterflow/config-template.yml
piwaterflow/config_waterflow.py
piwaterflow/waterflow.py
piwaterflow/tests/__init__.py
piwaterflow/tests/test_000.py
tests/__init__.py
tests/test_000_loop.py
tests/test_001_forward.py
tests/test_002_reverse.py
tests/test_003_lock.py
tests/test_004_events.py
piwaterflow-1.0.1.dist-info/METADATA
piwaterflow-1.0.1.dist-info/WHEEL
piwaterflow-1.0.1.dist-info/top_level.txt
piwaterflow-1.0.1.dist-info/RECORD
