Metadata-Version: 2.1
Name: piwaterflow
Version: 1.0.1
Summary: Raspberry Pi Waterflow resilient system
Home-page: https://github.com/Phornee/piwaterflow
Author: Ismael Raya
Author-email: phornee@gmail.com
License: UNKNOWN
Platform: UNKNOWN
Classifier: Programming Language :: Python :: 3
Classifier: License :: OSI Approved :: MIT License
Classifier: Operating System :: OS Independent
Classifier: Topic :: Home Automation
Requires-Python: >=3.6
Requires-Dist: log-mgr (>=0.1.1)
Requires-Dist: config-yml (>=0.3.1)
Requires-Dist: RPi.GPIO (>=0.7.0)
Requires-Dist: fake-rpigpio (>=0.1.1)
Requires-Dist: influxdb-wrapper (>=0.0.5)
